url2kindle.py
url2kindle-0.8.dist-info/LICENSE
url2kindle-0.8.dist-info/METADATA
url2kindle-0.8.dist-info/WHEEL
url2kindle-0.8.dist-info/entry_points.txt
url2kindle-0.8.dist-info/top_level.txt
url2kindle-0.8.dist-info/RECORD
