Metadata-Version: 2.1
Name: url2kindle
Version: 0.8
Summary: Send web articles to your Kindle from terminal
Home-page: https://github.com/silenc3r/url2kindle
Author: Dawid Zych
Author-email: dwd@mailo.com
License: MIT
Project-URL: Bug Tracker, https://github.com/silenc3r/url2kindle/issues
Platform: UNKNOWN
Classifier: Programming Language :: Python :: 3
Classifier: License :: OSI Approved :: MIT License
Classifier: Programming Language :: Python :: 3.6
Classifier: Programming Language :: Python :: 3.7
Classifier: Programming Language :: Python :: 3.8
Classifier: Programming Language :: Python :: 3.9
Classifier: Programming Language :: Python :: 3.10
Classifier: Programming Language :: Python :: 3 :: Only
Classifier: Environment :: Console
Requires-Python: >=3.6
License-File: LICENSE
Requires-Dist: requests
